[{"table":"C","no":"009/C/NBP/2022","tradingDate":"2022-01-13","effectiveDate":"2022-01-14","rates":[{"currency":"dolar amerykański","code":"USD","bid":3.9128,"ask":3.9918},{"currency":"dolar australijski","code":"AUD","bid":2.8595,"ask":2.9173},{"currency":"dolar kanadyjski","code":"CAD","bid":3.1401,"ask":3.2035},{"currency":"euro","code":"EUR","bid":4.4896,"ask":4.5802},{"currency":"forint (Węgry)","code":"HUF","bid":0.01266,"ask":0.012916},{"currency":"frank szwajcarski","code":"CHF","bid":4.3006,"ask":4.3874},{"currency":"funt szterling","code":"GBP","bid":5.3787,"ask":5.4873},{"currency":"jen (Japonia)","code":"JPY","bid":0.034231,"ask":0.034923},{"currency":"korona czeska","code":"CZK","bid":0.1836,"ask":0.1874},{"currency":"korona duńska","code":"DKK","bid":0.6033,"ask":0.6155},{"currency":"korona norweska","code":"NOK","bid":0.4519,"ask":0.4611},{"currency":"korona szwedzka","code":"SEK","bid":0.4395,"ask":0.4483},{"currency":"SDR (MFW)","code":"XDR","bid":5.5354,"ask":5.6472}]}]orona norweska","code":"NOK","mid":0.4556},{"currency":"korona szwedzka","code":"SEK","mid":0.4422},{"currency":"kuna (Chorwacja)","code":"HRK","mid":0.6035},{"currency":"lej rumuński","code":"RON","mid":0.9179},{"currency":"lew (Bułgaria)","code":"BGN","mid":2.3198},{"currency":"lira turecka","code":"TRY","mid":0.2920},{"currency":"nowy izraelski szekel","code":"ILS","mid":1.2727},{"currency":"peso chilijskie","code":"CLP","mid":0.00485},{"currency":"peso filipińskie","code":"PHP","mid":0.0771},{"currency":"peso meksykańskie","code":"MXN","mid":0.1951},{"currency":"rand (Republika Południowej Afryki)","code":"ZAR","mid":0.2584},{"currency":"real (Brazylia)","code":"BRL","mid":0.7161},{"currency":"ringgit (Malezja)","code":"MYR","mid":0.9476},{"currency":"rubel rosyjski","code":"RUB","mid":0.0520},{"currency":"rupia indonezyjska","code":"IDR","mid":0.00027696},{"currency":"rupia indyjska","code":"INR","mid":0.053413},{"currency":"won południowokoreański","code":"KRW","mid":0.003334},{"currency":"yuan renminbi (Chiny)","code":"CNY","mid":0.6235},{"currency":"SDR (MFW)","code":"XDR","mid":5.5706}]}]]